netbox_software_tracker/__init__.py
netbox_software_tracker/filtersets.py
netbox_software_tracker/forms.py
netbox_software_tracker/models.py
netbox_software_tracker/navigation.py
netbox_software_tracker/tables.py
netbox_software_tracker/urls.py
netbox_software_tracker/version.py
netbox_software_tracker/views.py
netbox_software_tracker/api/__init__.py
netbox_software_tracker/api/serializers.py
netbox_software_tracker/api/urls.py
netbox_software_tracker/api/views.py
netbox_software_tracker/migrations/0001_netbox_software_tracker.py
netbox_software_tracker/migrations/__init__.py
netbox_software_tracker/templates/netbox_software_tracker/goldenimage_list.html
netbox_software_tracker/templates/netbox_software_tracker/goldenimage_progress.html
netbox_software_tracker/templates/netbox_software_tracker/softwareimage.html
netbox_software_tracker-0.3.7.dist-info/LICENSE
netbox_software_tracker-0.3.7.dist-info/METADATA
netbox_software_tracker-0.3.7.dist-info/WHEEL
netbox_software_tracker-0.3.7.dist-info/top_level.txt
netbox_software_tracker-0.3.7.dist-info/RECORD
