Metadata-Version: 2.2
Name: netbox-software-tracker
Version: 0.3.7
Summary: Software and golden images for netbox devices
Home-page: https://github.com/jysk-network/netbox-software-tracker
Author: Patrick Falk Nielsen
Author-email: panie@jysk.com
License-File: LICENSE
Dynamic: author
Dynamic: author-email
Dynamic: description
Dynamic: description-content-type
Dynamic: home-page
Dynamic: summary
